SapGuiLibraryExtended/SapGuiLibraryExtended.py
SapGuiLibraryExtended/__init__.py
SapGuiLibraryExtended-0.4.7.dist-info/METADATA
SapGuiLibraryExtended-0.4.7.dist-info/WHEEL
SapGuiLibraryExtended-0.4.7.dist-info/top_level.txt
SapGuiLibraryExtended-0.4.7.dist-info/RECORD
